LICENSE
MANIFEST.in
README.rst
REQUIREMENTS
distribute_setup.py
hotqueue.py
setup.py
tests.py
hotqueue.egg-info/PKG-INFO
hotqueue.egg-info/SOURCES.txt
hotqueue.egg-info/dependency_links.txt
hotqueue.egg-info/requires.txt
hotqueue.egg-info/top_level.txt