Metadata-Version: 1.0
Name: hotqueue
Version: 0.2.7
Summary: HotQueue is a Python library that allows you to use Redis as a message queue within your Python programs.
Home-page: http://github.com/richardhenry/hotqueue
Author: Richard Henry
Author-email: richardhenry@me.com
License: MIT
Platform: UNKNOWN
Classifier: Programming Language :: Python
Classifier: Development Status :: 4 - Beta
Classifier: Intended Audience :: Developers
Classifier: License :: OSI Approved :: MIT License
Classifier: Operating System :: OS Independent
Classifier: Topic :: Software Development :: Libraries :: Python Modules
